fl_manager/lightning/__init__.py
fl_manager/lightning/py.typed
fl_manager/lightning/components/__init__.py
fl_manager/lightning/components/callbacks/__init__.py
fl_manager/lightning/components/callbacks/lightning_callback_registry.py
fl_manager/lightning/components/callbacks/nvflare_callbacks_wrappers.py
fl_manager/lightning/components/callbacks/base/__init__.py
fl_manager/lightning/components/callbacks/base/ditto_fl_callback.py
fl_manager/lightning/components/callbacks/base/fed_avg_fl_callback.py
fl_manager/lightning/components/callbacks/base/fed_bn_fl_callback.py
fl_manager/lightning/components/callbacks/base/fed_opt_fl_callback.py
fl_manager/lightning/components/callbacks/base/fed_prox_fl_callback.py
fl_manager/lightning/components/datamodule/__init__.py
fl_manager/lightning/components/datamodule/base_lightning_datamodule.py
fl_manager/lightning/components/datamodule/lightning_datamodule_registry.py
fl_manager/lightning/components/datamodule/base/__init__.py
fl_manager/lightning/components/datamodule/base/default_datamodule.py
fl_manager/lightning/components/datamodule/base/tokenizer_datamodule.py
fl_manager/lightning/dataflows/__init__.py
fl_manager/lightning/dataflows/base_lightning_trainer.py
fl_manager/lightning/executors/__init__.py
fl_manager/lightning/executors/lightning_fl_executor.py
fl_manager/lightning/executors/stateful_lightning_fl_executor.py
fl_manager/lightning/executors/stateless_ditto_lightning_fl_executor.py
fl_manager/lightning/executors/stateless_lightning_fl_executor.py
fl_manager/lightning/executors/nv/__init__.py
fl_manager/lightning/executors/nv/nvflare_lightning_executor.py
fl_manager/lightning/executors/nv/stateful_nvflare_lightning_executor.py
fl_manager/lightning/executors/nv/stateless_ditto_nvflare_lightning_executor.py
fl_manager/lightning/executors/nv/stateless_nvflare_lightning_executor.py
fl_manager/lightning/utils/__init__.py
fl_manager/lightning/utils/lightning_callback_wrapper.py
fl_manager/lightning/utils/lightning_utils.py
fl_manager_lightning-0.1.0.dist-info/METADATA
fl_manager_lightning-0.1.0.dist-info/WHEEL
fl_manager_lightning-0.1.0.dist-info/licenses/LICENSE
fl_manager_lightning-0.1.0.dist-info/RECORD
